replace_accents/__init__.py
replace_accents/src/__init__.py
replace_accents/src/replace_accents_characters.py
replace_accents-0.0.5.dist-info/LICENSE
replace_accents-0.0.5.dist-info/METADATA
replace_accents-0.0.5.dist-info/WHEEL
replace_accents-0.0.5.dist-info/top_level.txt
replace_accents-0.0.5.dist-info/RECORD
