Metadata-Version: 2.1
Name: replace_accents
Version: 0.0.5
Summary: This package helps to replace accented characters with their corresponding non-accented ascii characters
Home-page: https://medium.com/@rahul.madhani/replace-accented-characters-in-python-pyspark-and-spark-sql-28844b6c783e
Author: Rahul Madhani
Author-email: madhani.rahul@gmail.com
Project-URL: Documentation, https://medium.com/@rahul.madhani/replace-accented-characters-in-python-pyspark-and-spark-sql-28844b6c783e
Project-URL: Source, https://github.com/madhanir/replace_accents
Classifier: Development Status :: 5 - Production/Stable
Classifier: Intended Audience :: Developers
Classifier: License :: OSI Approved :: MIT License
Classifier: Natural Language :: English
Classifier: Operating System :: OS Independent
Classifier: Programming Language :: Cython
Classifier: Programming Language :: Python
Classifier: Topic :: Scientific/Engineering
Classifier: Topic :: Software Development :: Libraries
Classifier: Topic :: Software Development :: Libraries :: Python Modules
Classifier: Topic :: Text Processing
License-File: LICENSE
